{
  " does not exist": " 不存在",
  " File Name": " 文件名",
  ".{Extension} file located on your computer, eg: C:/Users/me/Downloads/awesome.{Extension}": "位于你电脑上的 .{Extension} 文件(如: C:/Users/me/Downloads/awesome.{Extension})",
  ".atex to DDS": ".atex 转 DDS",
  ".atex to PNG": ".atex 转 PNG",
  "[GetResourceHandler] Original {0} -> {1} -> {2}": "[GetResourceHandler] 原函数 {0} -> {1} -> {2}",
  "[GetResourceHandler] Replace {0} -> {1} -> {2}": "[GetResourceHandler] 替换 {0} -> {1} -> {2}",
  "[NONE]": "[无]",
  "[ReadSqpackHandler] Calling Original With {0}": "[ReadSqpackHandler] 使用 {0} 调用原函数",
  "[ReadSqpackHandler] Replaced with {0}": "[ReadSqpackHandler] 已使用 {0} 替换",
  "[TEMPLATE]": "[模板]",
  "[UNKNOWN]": "[未知]",
  "[WIP]": "[工作中]",
  "{Entry.Format} / {Entry.NumChannels} Ch / {Entry.SampleRate}Hz / 0x{Entry.DataLength:X8} bytes": "{Entry.Format} / {Entry.NumChannels} 声道 / {Entry.SampleRate}Hz / 0x{Entry.DataLength:X8} 字节",
  "{HeaderText} ({Selected.Count} Selected / {Group.Items.Count})###ExportUI/{HeaderText}": "{HeaderText} (已选中 {Selected.Count} / {Group.Items.Count})###ExportUI/{HeaderText}",
  "{IdUpperCase} Being Replaced": "被替换的{IdUpperCase}",
  "{IdUpperCase} file loaded": "已加载 {IdUpperCase} 文件",
  "{ItemName}-SPLIT": "{ItemName}-分隔",
  "{name} [DOCUMENTS]": "{name} [文档]",
  "{Name}-FAVORITE": "{Name}-收藏",
  "{Selected.Name} Cast": "{Selected.Name} 咏唱",
  "{SelectedFileNames.Count} files Selected": "已选择 {SelectedFileNames.Count} 个文件",
  "+ New": "+ 新建",
  "+ NEW": "+ 新增",
  "+ Simple Animation": "+ 简易动画",
  "3D View": "3D 视图",
  "A workspace allows you to save multiple vfx replacements at the same time, as well as any imported textures or item renaming (such as particles or emitters)": "工作区允许你一次保存多个视效的替换、导入的材质以及物品重命名(如: 粒子效果、触发器)",
  "AB Group Number": "AB 组编号",
  "Above character?": "角色上方?",
  "Acceleration": "加速",
  "Acceleration #{idx}": "加速 #{idx}",
  "Acceleration Count": "加速计数",
  "Action": "技能",
  "Active": "激活时的颜色",
  "Actor {idx}": "角色 {idx}",
  "Add to node library": "添加到节点库",
  "Affect Game": "影响游戏",
  "Affect Other VFX": "影响其他视效",
  "Air Resistance": "空气阻力",
  "Air Resistance Random": "随机空气阻力",
  "All Stop on Hide": "隐藏时全部停止",
  "Allow Show": "允许显示",
  "Already Adpcm, skipping conversion": "已经为 ADPCM 格式，跳过转换",
  "Ambient": "环境",
  "Angle": "角度",
  "Angle X": "X 轴角度",
  "Angle X Random": "随机 X 轴角度",
  "Angle Y": "Y 轴角度",
  "Angle Y Random": "随机 Y 轴角度",
  "Angle Z": "Z 角度",
  "Animation": "动画",
  "Animation - PAP Only": "动画 - 角色专用",
  "Animation canceled by movement": "被移动取消的动画",
  "Animation Cancelled by Movement": "被移动取消的动画",
  "Animation End Frame": "动画结束帧",
  "Animation Id": "动画 ID",
  "Animation Lock": "动画锁",
  "Animation Number": "动画编号",
  "Animation Start Frame": "动画起始帧",
  "Animations": "动画",
  "AnimationTabs": "动画栏",
  "Any Direction": "任意方向",
  "Argument Count": "参数数量",
  "Astrologian": "占星术士",
  "Attenuation": "衰减",
  "Attribute Id": "属性 ID",
  "Attributes": "属性",
  "Audio": "音频",
  "Audio files{.ogg,.wav},.*": "音频文件{.ogg,.wav},.*",
  "Audio files{.wav},.*": "音频文件{.wav},.*",
  "Audio Index": "音频序列",
  "Audio player settings. These do not have any effect on the .scd file": "音频播放器设置。不会影响 .scd 文件",
  "Aura F": "敖龙族女性",
  "Aura M": "敖龙族男性",
  "Author": "作者",
  "Auto-Attack": "自动攻击",
  "Auto-Attack {i + 1}": "自动攻击 {i + 1}",
  "Autosave time (seconds)": "自动保存时间间隔 (秒)",
  "Autosave workspace": "自动保存工作区",
  "aximum Number of People": "最大人数",
  "Axis Connect": "轴连接",
  "Axis Connect Random": "随机轴连接",
  "Background": "背景色",
  "Bar color": "顶栏颜色",
  "Bard": "吟游诗人",
  "Base Direction Type": "基准方向类型",
  "Be careful about modifying this file, as it contains dozens of animations for every job": "请谨慎修改此文件，此文件包含了为每个职业设计大量的动画",
  "Bias Z Max Distance": "Z 轴最大距离偏移",
  "Bias Z Max Scale": "Z 轴最大缩放值偏移",
  "Bind Id": "绑定 ID",
  "Bind Parent": "绑定父级",
  "Bind Point {item.BindPointId}": "绑定点 {item.BindPointId}",
  "Bind Point 1": "绑定点 1",
  "Bind Point 2": "绑定点 2",
  "Bind Point 3": "绑定点 3",
  "Bind Point 4": "绑定点 4",
  "Bind Point ID": "绑定点 ID",
  "Bind Weapon": "绑定武器",
  "Bind Weapon Type": "绑定武器类型",
  "Binder Index": "绑定器索引",
  "Binder Select": "选择绑定器",
  "Binders": "绑定器",
  "Black Mage": "黑魔法师",
  "Blank": "空白",
  "Block game inputs when VFXEditor is focused##Settings": "当 VFXEditor 窗口处于活动状态时屏蔽游戏内输入##Settings",
  "Block Number": "区块编号",
  "Blue Mage": "青魔法师",
  "Body Id": "身体 ID",
  "BodyId": "身体 ID",
  "Bone Name": "骨骼名",
  "Bright": "亮度",
  "Bus Ducking": "总线下降",
  "Bus Number": "总线编号",
  "By Injection Angle": "通过注射角度",
  "By Injection Angle X": "通过 X 轴注射角度",
  "By Injection Angle Y": "通过 Y 轴注射角度",
  "By Injection Angle Z": "通过 Z 轴注射角度",
  "Calculation Type": "计算类型",
  "Camera Space": "摄像机空间",
  "Can be Clipped Out": "可被裁剪",
  "Cancel": "取消",
  "Cast": "咏唱",
  "Center FAC": "中心效应强度系数",
  "Center of the character": "角色中心",
  "Center Offset": "中心偏移",
  "Cervical": "颈部",
  "CF (Unknown)": "CF (未知)",
  "Changes to the temp file location may require a restart to take effect": "对缓存文件位置的修改可能需要通过重启游戏来生效",
  "Changes to this file are potentially detectable": "对该文件的修改可能会被检测",
  "Channel #{Channel1}": "声道 #{Channel1}",
  "Channel #{Channel2}": "声道 #{Channel2}",
  "Channel #{i}": "声道 #{i}",
  "Channels": "声道",
  "Character": "角色",
  "Child": "子级",
  "Child Limit": "子级限制",
  "Clean up": "清除",
  "Clear": "清除",
  "Clip {ClipIdx.GetValue()}": "片段 {ClipIdx.GetValue()}",
  "Clip {GetIdx()}({Type.Text})": "片段 {GetIdx()}({Type.Text})",
  "Clip Box Enabled": "启用裁剪框",
  "Clip Box Position": "裁剪框位置",
  "Clip Box Size": "裁剪框大小",
  "Clip Box Size X": "裁剪框 X 轴尺寸",
  "Clip Box Size Y": "裁剪框 Y 轴尺寸",
  "Clip Box Size Z": "裁剪框 Z 轴尺寸",
  "Clip Box X": "裁剪框 X 坐标",
  "Clip Box Y": "裁剪框 Y 坐标",
  "Clip Box Z": "裁剪框 Z 坐标",
  "Clip Count": "片段数",
  "Clip Enabled": "启用片段",
  "Clip Index": "片段索引",
  "Clip Own Setting": "裁剪自身",
  "Clips": "片段",
  "Close Time": "结束时间",
  "Collapsed": "折叠时的颜色",
  "Color": "颜色",
  "Color 1": "颜色 1",
  "Color 2": "颜色 2",
  "Color 3": "颜色 3",
  "Color 4": "颜色 4",
  "Color Begin": "起始颜色",
  "Color Center": "中心颜色",
  "Color Edge Begin": "起始颜色渐变",
  "Color Edge Center": "中心颜色渐变",
  "Color Edge End": "结束颜色渐变",
  "Color Edge Inner": "内部边缘颜色",
  "Color Edge Outer": "外部边缘颜色",
  "Color End": "结束颜色",
  "Color ring width": "颜色环宽度",
  "Color:{hasColor} UV2:{hasUv2}": "颜色:{hasColor} UV2:{hasUv2}",
  "Common": "通常",
  "Configuration": "设置",
  "Confirm": "确认",
  "Connect Target": "连接目标",
  "Connect Target Reverse": "连接目标反转",
  "Constructor failed for {magic}": "构造函数由于 {magic} 发生错误",
  "Convergence FAC": "汇聚强度系数",
  "Convertor": "转换器",
  "Coord Accuracy": "坐标精确度",
  "Coord Accuracy X": "X 轴坐标精度",
  "Coord Accuracy Y": "Y 轴坐标精度",
  "Coord Accuracy Z": "Z 轴坐标精度",
  "Coord Gra": "坐标梯度",
  "Coord Gra X": "X 轴坐标梯度",
  "Coord Gra Y": "Y 轴坐标梯度",
  "Coord Gra Z": "Z 轴坐标梯度",
  "Coordinate Compute Order": "坐标计算顺序",
  "Copy": "复制",
  "Could not conver to ADPCM": "无法转换为 ADPCM",
  "Could not export to Penumbra": "无法导出至 Penumbra",
  "Could not export to TexTools": "无法导出至 TexTools",
  "Could not find file: {sklbPath}": "无法找到文件: {sklbPath}",
  "Could not find header": "无法找到标题",
  "Could not find pages": "无法找到页面",
  "Could not find tex: ": "无法找到材质: ",
  "Could not import": "无法导入",
  "Could not import data": "无法导入数据",
  "Could not load workspace": "工作区加载失败",
  "Could not read file": "无法读取文件",
  "Could not read file: {sklbPath}": "无法读取文件: {sklbPath}",
  "Count": "数量",
  "Crafting Delay": "生产延迟",
  "Create Area": "创建区域",
  "Create Area X": "创建 X 轴区域",
  "Create Area Y": "创建 Y 轴区域",
  "Create Area Z": "创建 Z 轴区域",
  "Create Count": "创建数",
  "Create Count Interval": "创建数间隔",
  "Create Count Interval Random": "随机创建数间隔",
  "Create Count Random": "随机创建数",
  "Create Directory": "新建文件夹",
  "Create Distance Far": "创建远距离效果",
  "Create Distance Near": "创建近距离效果",
  "Create Emitters": "创建发射器",
  "Create Interval": "创建间隔",
  "Create Interval Count": "创建间隔数",
  "Create Interval Life": "创建间隔生命周期",
  "Create Interval Random": "随机创建间隔",
  "Create Line Type": "创建线型",
  "Create New After Death": "死亡后创建新对象",
  "Create Particles": "创建粒子",
  "Create Probability": "创建概率",
  "Create Time": "创建时间",
  "Curve Editor": "曲线编辑器",
  "Curve editor controls (?)": "曲线编辑器控制 (?)",
  "CustomFourCC must have four characters only.": "自定义四人角色编码必须有且只有四名玩家",
  "Cutscene": "过场动画",
  "Cycle Interval": "循环间隔",
  "Cycle Play Track": "循环播放音轨",
  "Cycle Range": "循环范围",
  "Dancer": "舞者",
  "Dark Knight": "暗黑骑士",
  "Date": "日期",
  "Default": "默认",
  "Degrees": "度",
  "Delay Fast Particle": "延迟快速粒子",
  "Delete": "删除",
  "Delete {name}": "删除 {name}",
  "Description": "描述",
  "Desktop": "桌面",
  "Direct Volume 1": "直接音量 1",
  "Direct Volume 2": "直接音量 2",
  "Direction": "方向",
  "Directional Light Source": "定向光源",
  "Directional Light Type": "定向光源类型",
  "Directory Path :": "目录路径 :",
  "Distance Scale": "距离缩放",
  "Divide X": "X 轴分割",
  "Divide Y": "Y 轴分割",
  "DO NOT modify movement abilities (dashes, backflips). Please read a guide before attempting to modify a .tmb or .pap file": "请 不要 修改移动类技能 (冲刺、后跳等)。尝试修改 .tmb 或 .pap 文件前请先阅读指南",
  "Documents": "文档",
  "Don't add or remove entries in this file": "请不要在此文件中增加或移除任何条目",
  "Doppler FAC": "多普勒效应强度系数",
  "Double-click to navigate to items": "双击以导航至物体",
  "Down Time": "停止时间",
  "Dragoon": "龙骑士",
  "Draw Layer": "绘制层级",
  "Draw Order": "绘制顺序",
  "Duplicate": "复制",
  "Duration": "持续时间",
  "Edit": "编辑",
  "Effector": "效果器",
  "Effector Index": "效果器索引",
  "Effector Select": "效果器选择",
  "Effectors": "效果器",
  "Eid Editor": "角色编辑器",
  "Elezen F": "精灵族女性",
  "Elezen M": "精灵族男性",
  "Emitter": "发射器",
  "Emitter {GetIdx()}({EmitterVariety.GetValue()})": "发射器 {GetIdx()}({EmitterVariety.GetValue()})",
  "Emitter Count": "发射器数",
  "Emitter Index": "发射器索引",
  "Emitter Vertices": "发射器顶点",
  "Emitters": "发射器",
  "Emote": "表情",
  "Enable Char Shadow": "启用角色阴影",
  "Enable Filter": "启用筛选器",
  "Enable Map Shadow": "启用地图阴影",
  "Enable Shadow": "启用阴影",
  "Enabled": "启用",
  "Enabled Move Shadow": "启用移动阴影",
  "End": "结束",
  "End Position": "结束位置",
  "End Time": "结束时间",
  "End Visibility": "可见性结束",
  "Error compiling shaders": "编译着色器时发生错误",
  "Error executing": "执行过程中发生错误",
  "Error importing {localPath} into {gamePath}": "从 {localPath} 导入进 {gamePath} 时发生错误",
  "Error loading IMC file ": "加载 IMC 文件 时发生错误",
  "Error Loading: ": "加载时发生错误: ",
  "Error playing sound": "播放音效时发生错误",
  "Error reading ": "读取时发生错误 ",
  "Error reading file": "读取文件时发生错误",
  "Error Reading File": "读取文件时发生错误",
  "Error reading files": "读取文件时发生错误",
  "Error reading Penumbra mods": "读取 Penumbra 模组时发生错误",
  "Export": "导出",
  "Export {entry.Key}": "导出 {entry.Key}",
  "Export all Havok data": "导出所有的 Havok 数据",
  "Export Dependencies": "导出依赖关系",
  "Export sound file to .wav or .ogg": "导出音效文件为 .wav 或 .ogg 格式",
  "Export TMB": "导出时间线",
  "Exported from VFXEditor": "由 VFXEditor 导入",
  "Exported To: ": "导出至: ",
  "ExportedSound": "音频导出",
  "Exports the selected items:as well as any dependencies they have (such as particles depending on textures). It is recommended to leave this selected.": "导出选中的物体与它们各自拥有的依赖关系(比如说依赖于材质的粒子)。推荐保持此项选中",
  "Extend 1": "扩展 1",
  "Extend 2": "扩展 2",
  "Extend 3": "扩展 3",
  "Extend 4": "扩展 4",
  "Extra": "额外",
  "Extra Data": "额外数据",
  "Extract": "解压",
  "Extract Raw Game File": "解压原始游戏文件",
  "Face {face}": "面部 {face}",
  "Face Library Path": "面部库路径",
  "Fade Enabled X": "启用 X 轴上淡化效果",
  "Fade Enabled Y": "启用 Y 轴上淡化效果",
  "Fade Enabled Z": "启用 Z 轴上淡化效果",
  "Fade End Distance": "结束淡出距离",
  "Fade In": "淡入",
  "Fade Inner": "内部淡化",
  "Fade Inner X": "X 轴内部淡化",
  "Fade Inner Y": "Y 轴内部淡化",
  "Fade Inner Z": "Z 轴内部淡化",
  "Fade Out Duration": "淡出持续时间",
  "Fade Outer": "外部淡化",
  "Fade Outer X": "X 轴外部淡化",
  "Fade Outer Y": "Y 轴外部淡化",
  "Fade Outer Z": "Z 轴外部淡化",
  "Fade Range": "淡化范围",
  "Fade Start Distance": "开始淡出距离",
  "Fade Time": "淡化时间",
  "Far Clip Begin": "远裁剪起始位置",
  "Far Clip End": "远裁剪结束位置",
  "Far Delay FAC": "远距离延迟强度系数",
  "Favorites": "收藏",
  "File {fileIdx}": "文件 {fileIdx}",
  "File Editors": "文件编辑器",
  "File Name :": "文件名",
  "File picker image preview": "选择文件时预览图像",
  "Filter": "筛选器",
  "Filter {idx}": "筛选器 {idx}",
  "Filter Count": "筛选器数",
  "Final Position": "最终位置",
  "First Condition": "第一条件",
  "Fit Ground": "适应地面",
  "Fit To Contents": "自适应显示",
  "Fixed Direction": "固定方向",
  "Flag": "标识",
  "Flags": "标识",
  "File": "文件",
  "Flinch": "受击",
  "Fly Text": "漂浮文本",
  "Fly Text Settings": "漂浮文本设置",
  "Footstep": "脚步",
  "Format: {texture.Format}  Mips: {texture.MipLevels}  Size: {texture.Width}x{texture.Height}": "格式: {texture.Format}  纹理金字塔层级: {texture.MipLevels}  大小: {texture.Width}x{texture.Height}",
  "Frame": "帧",
  "Frame 1": "帧 1",
  "Frame 2": "帧 2",
  "Frame 3": "帧 3",
  "Frame 4": "帧 4",
  "FreeImage Library loaded: {TeximpNet.Unmanaged.FreeImageLibrary.Instance.IsLibraryLoaded}": "已加载 FreeImage 库: {TeximpNet.Unmanaged.FreeImageLibrary.Instance.IsLibraryLoaded}",
  "Freeze Position": "冻结位置",
  "Fresnel Curve": "菲涅尔曲线",
  "Fresnel Rotation": "菲涅尔旋转",
  "Fresnel Type": "菲涅尔类型",
  "Front of character": "角色前方",
  "Full Env Light": "全局环境光",
  "Function Number": "函数编号",
  "Game Items": "游戏物品",
  "Game Path": "游戏路径",
  "Gathering Delay": "采集延迟",
  "General": "一般",
  "Generate Delay": "生成延迟",
  "Generate Delay By One": "生成 1 单元延迟",
  "Generate Method": "生成方法",
  "Gimmick": "机制",
  "Github##ResLogger": "GitHub##ResLogger",
  "Global Fog": "全局烟雾效果",
  "Global Fog Influence": "全局雾效影响",
  "Grab distance": "选取距离",
  "Gradation": "渐变",
  "Gravity": "重力",
  "Gravity Random": "随机重力",
  "Group Number": "组数",
  "Guide##NoVfx": "指南##NoVfx",
  "Guides##Pap": "指南##Pap",
  "Gunbreaker": "绝枪战士",
  "Hash": "哈希值",
  "Havok data imported": "已导入 Havok 数据",
  "Havok data removed": "已移除 Havok 数据",
  "Havok data replaced": "Havok 数据已被替换",
  "Head": "头部",
  "Head (near left eye )": "头部 (偏左眼)",
  "Head (near right eye)": "头部 (偏右眼)",
  "Height": "高度",
  "Height Begin Inner": "内部起始高度",
  "Height Begin Outer": "外部开始高度",
  "Height End Inner": "内部结束高度",
  "Height End Outer": "外部结束高度",
  "Help": "帮助",
  "Here": "这里",
  "Hi-Cut FAC": "高频截止强度系数",
  "Hide": "隐藏",
  "Hide with UI": "跟随 UI 隐藏",
  "Highlander F": "高地之民女性",
  "Highlander M": "高地之民男性",
  "Hit": "命中",
  "Housing": "房屋",
  "Hrothgar M": "硌狮族男性",
  "Idle": "闲置动作",
  "Image Conversion": "图像转换",
  "Image files{.png,.": "图片文件{.png,.",
  "Import": "导入",
  "Import File": "导入文件",
  "Import Texture": "导入材质",
  "Imported MDL mesh": "已导入 MDL 模型网格",
  "Importing GLTF from: ": "导入 GLTF 中: ",
  "Importing MDL from: ": "导入 MDL 中: ",
  "Indices not multiples of 3": "索引数非 3 的倍数",
  "Influence Coordinate Unstickiness": "对坐标不粘性的影响",
  "Influence on Binder Position": "对绑定点位置的影响",
  "Influence on Child": "对子级的影响",
  "Influence on Child Color": "对子级颜色的影响",
  "Influence on Position": "对位置的影响",
  "Influence on Rotation": "对旋转的影响",
  "Influence on Scale": "对缩放的影响",
  "Inherit Parent Life": "继承父级生命周期",
  "Inherit Parent Velocity": "继承父级速度",
  "Injection Angle": "注入角度",
  "Injection Angle Random": "随机注入角度",
  "Injection Angle X": "X 轴注入角度",
  "Injection Angle X Random": "随机 X 轴注入角度",
  "Injection Angle Y": "Y 轴注入角度",
  "Injection Angle Y Random": "随机 Y 轴注入角度",
  "Injection Direction Type": "注入方向类型",
  "Injection Model": "注入模型",
  "Injection Model Bind Index": "注入模型绑定索引",
  "Injection Model Index": "注入模型索引",
  "Injection Position Type": "注入位置类型",
  "Injection Radial Direction 0": "辐射方向注入 - 0",
  "Injection Radial Direction 1": "辐射方向注入 - 1",
  "Injection Speed": "注入速度",
  "Injection Speed Random": "随机注入速度",
  "Injection Vertex Bind Model": "注入顶点绑定模型",
  "Inner Radius": "内半径",
  "Inner Size": "内尺寸",
  "Instance": "副本",
  "Interior FAC": "内部效应强度系数",
  "Interrupt": "打断",
  "Invalid format: {ret.Format} {gamePath}": "无效格式: {ret.Format} {gamePath}",
  "Invalid path! Could not find DatFile": "无效路径! 未找到 Dat 文件",
  "Invisibility": "不可见",
  "Is Lightning": "是否点亮",
  "Is Local": "是否位于本地",
  "Is Morph": "是否变形",
  "Is Spline": "是否为样条曲线",
  "Item Count": "物体数",
  "Items": "物体",
  "Job": "职业",
  "Join Type": "连接类型",
  "Journal Cutscene": "可回放过场动画",
  "Keybinds": "按键绑定",
  "Kill": "终止",
  "Lalafell F": "拉拉菲尔族女性",
  "Lalafell M": "拉拉菲尔族男性",
  "Layouts": "布局",
  "Left": "左",
  "Left calves": "左小腿",
  "Left foot": "左脚",
  "Left forearm": "左前臂",
  "Left hand": "左手",
  "Left hand weapon": "左手武器",
  "Left shoulder": "左肩",
  "Lemure ": "附体",
  "Length": "长度",
  "Length Random": "随机长度",
  "Library": "库",
  "Line color": "线颜色",
  "Line Count": "线数",
  "Line Length Max": "最长线长",
  "Line Length Min": "最短线长",
  "Line width": "线宽",
  "Live overlay limit by distance": "实时叠加层距离限制",
  "Live overlay remove delay time": "实时叠加层移除延迟时间",
  "Load Animation": "加载动画",
  "Loaded {IdUpperCase}": "已加载的{IdUpperCase}",
  "Loading ": "正在加载 ",
  "Local Direction": "本地方向",
  "Local File": "本地文件",
  "Local file: [{localPath}] does not exist": "本地文件: [{localPath}] 不存在",
  "Local Id": "本地 ID",
  "Local Number": "本地编号",
  "Lock Facing Direction": "锁定面向",
  "Log all files": "记录所有文件",
  "Log debug information": "记录 DEBUG 信息",
  "Log Vfx debug information": "记录视效 DEBUG 信息",
  "Loop": "循环",
  "Loop 1": "循环 1",
  "Loop 2": "循环 2",
  "Loop 3": "循环 3",
  "Loop End": "循环结束",
  "Loop Music": "循环音乐",
  "Loop Sound Effect": "循环音效",
  "Loop Start": "循环开始",
  "Loop Start/End (Bytes)": "循环开始/结束 (字节)",
  "Looping...": "循环中",
  "Lower Limit": "下限",
  "LTS Enabled": "启用 LTS",
  "Machinist": "机工士",
  "Make sure the number of Sounds and Layouts is the same": "请确保音效和布局的数量保持一致",
  "Max Range": "范围最大值",
  "Midlander F": "中原之民女性",
  "Midlander M": "中原之民男性",
  "Min Range": "范围最小值",
  "Minimum Number of People": "最少人数",
  "Miquote F": "猫魅族女性",
  "Miquote M": "猫魅族男性",
  "Mismatched emit vertex counts {EmitVertexes.EmitVertexes.Count} {EmitVertexNumbers.VertexNumbers.Count}": "发射顶点数量不匹配 {EmitVertexes.EmitVertexes.Count} {EmitVertexNumbers.VertexNumbers.Count}",
  "Missing model data": "模型数据丢失",
  "Mod Name": "模组名",
  "Model": "模型",
  "Model Id": "模型 ID",
  "Model Index": "模型索引",
  "Model Number Random": "随机模型编号",
  "Model Number Random Interval": "随机模型编号间隔",
  "Model Number Random Type": "随机模型编号类型",
  "ModelId": "模型 ID",
  "Models": "模型",
  "ModelTabs": "模型栏",
  "Monk": "武僧",
  "Monsters weapon": "怪物武器",
  "Morph": "变形",
  "Mount": "坐骑",
  "Move A": "移动动作 A",
  "Move B": "移动动作 B",
  "Music": "音乐",
  "Navigate to selected node": "导航至选中的节点",
  "Near Clip Begin": "近裁剪起始位置",
  "Near Clip End": "近裁剪结束位置",
  "Near Fade End": "近距离淡出结束",
  "Near Fade Start": "近距离淡出开始",
  "New": "新建",
  "New Actor: {vfxPath} {vfx:X8}": "新角色: {vfxPath} {vfx:X8}",
  "New Directory Name": "新文件夹名称",
  "New Folder": "新建文件夹",
  "New Static: {vfxPath} {vfx:X8}": "新静态效果: {vfxPath} {vfx:X8}",
  "New Sub-Folder": "新建子文件夹",
  "Ninja": "忍者",
  "No Billboard": "无广告牌效果",
  "No data found": "未发现任何数据",
  "No description": "无描述",
  "No nodes saved...": "未保存任何节点...",
  "No textures have been imported...": "未导入任何材质...",
  "Node Graph": "节点图",
  "Node Library": "节点库",
  "Non-Player Action": "非玩家对象动作",
  "Normal": "法线",
  "Not Billboard Base Axis": "非广告牌基准轴",
  "Not working": "未工作",
  "Notes on using GLTF models": "使用 GLTF 模型的一些注意事项",
  "Npc": "NPC",
  "Npc file list provided by ResLogger": "请查阅由 ResLogger 提供的 NPC 文件列表",
  "Number of Conditions": "情况数",
  "NVT Default name: {nvtLib.DefaultLibraryName} Library loaded: {nvtLib.IsLibraryLoaded}": "NVT 默认名称: {nvtLib.DefaultLibraryName} 已加载库: {nvtLib.IsLibraryLoaded}",
  "NVT Library path: {nvtLib.LibraryPath} Library loaded: {nvtLib.IsLibraryLoaded}": "NVT 库路径: {nvtLib.LibraryPath} 已加载库: {nvtLib.IsLibraryLoaded}",
  "NVT TeximpNet paths: {nv_32bitPath} / {nv_64bitPath}": "NVT TeximpNet 路径: {nv_32bitPath} / {nv_64bitPath}",
  "NVTT Library loaded: {TeximpNet.Unmanaged.NvTextureToolsLibrary.Instance.IsLibraryLoaded}": "已加载 NVTT 库: {TeximpNet.Unmanaged.NvTextureToolsLibrary.Instance.IsLibraryLoaded}",
  "Object Control": "物体控制",
  "Object Position": "物体位置",
  "Object Scaling": "物体缩放",
  "Obstacle FAC": "障碍强度系数",
  "ocealot": "ocealot:AtmoOmen(本地化)",
  "Ok": "确定",
  "On Ground": "在地面",
  "On Self": "在自身",
  "On Target": "在目标",
  "Open": "打开",
  "Open Time": "开启时间",
  "Opened workspace": "打开工作区",
  "Orchestrion": "管弦乐琴音乐",
  "Order": "顺序",
  "Outer Radius": "外半径",
  "Outer Size": "外尺寸",
  "Override Life": "覆盖生命周期",
  "Override Life Random": "随机覆盖生命周期",
  "Override Life Value": "覆盖生命周期值",
  "Paladin": "骑士",
  "Pap Editor": "动画编辑器",
  "Parameter Link": "参数链接",
  "Parameters": "参数",
  "Parsing Issues": "解析出错",
  "Particle Count": "粒子数",
  "Particles": "粒子",
  "Parts Count": "组件数量",
  "Parts Count U": "水平组件数量",
  "Parts Count V": "垂直组件数量",
  "Paste": "粘贴",
  "Path": "路径",
  "Pictures": "图片",
  "Pitch": "音高",
  "Pivot X": "中心点 X",
  "Pivot Y": "中心点 Y",
  "Platform": "平台",
  "Play": "播放",
  "Play History": "播放历史",
  "Play Time Length": "播放时间长度",
  "Please don't do anything stupid with this": "请不要对此项做出任何修改",
  "PnDs (Unknown)": "PnDs (未知)",
  "PNG Format": "PNG 格式",
  "PNG Mip Levels": "PNG 纹理金字塔层级",
  "Point color": "点颜色",
  "Point Count": "点数量",
  "Point Count Center": "点数量中心",
  "Point Count End Distortion": "点数量末端失真",
  "Point Interval Factor V": "垂直点间隔因子",
  "Point Light 1": "点光源 1",
  "Point Light 2": "点光源 2",
  "Point Light Attenuation": "点光源衰减",
  "Point Light Type": "点光源类型",
  "Point size": "点大小",
  "POINTS ARE IN THE WRONG ORDER": "点的顺序错误",
  "Polyline Tag": "折线标签",
  "Pose {i}": "姿势 {i}",
  "Poses": "姿势",
  "Position": "位置",
  "Position 1": "位置 1",
  "Position 2": "位置 2",
  "Position 3": "位置 3",
  "Position 4": "位置 4",
  "Position Delay": "位置延迟",
  "Post Behavior": "后置行为",
  "Pount Count Center": "点数量中心",
  "Power": "强度",
  "Pre Behavior": "前置行为",
  "Preview Channel 1": "预览声道 1",
  "Preview Channel 2": "预览声道 2",
  "Primary selected color": "基础颜色",
  "Primary selected size": "基础大小",
  "Priority": "优先级",
  "Ptr": "指针",
  "Quest BGM": "任务 BGM",
  "Radians": "弧度",
  "Radius": "半径",
  "Radius Begin": "半径起始点",
  "Radius End": "半径结束点",
  "Radius In": "内半径",
  "Radius Out": "外半径",
  "Random A": "随机透明度",
  "Random B": "随机蓝色",
  "Random Bright": "随机亮度",
  "Random G": "随机绿色",
  "Random R": "随机红色",
  "Random Trigger": "随机触发器",
  "Random Type": "随机类型",
  "Random Value": "随机值",
  "Random X": "随机 X",
  "Random Y": "随机 Y",
  "Random Z": "随机 Z",
  "RandomType": "随机类型",
  "Range Volume": "范围音量",
  "Range X": "X 轴范围",
  "Range Y": "Y 轴范围",
  "Raw Float 1": "原始浮点数 1",
  "Raw Float 2": "原始浮点数 2",
  "Raw Float 3": "原始浮点数 3",
  "Raw Float 4": "原始浮点数 4",
  "Raw Floats": "原始浮点数",
  "Raw Int 1": "原始整数 1",
  "Raw Int 2": "原始整数 2",
  "Raw Int 3": "原始整数 3",
  "Raw Int 4": "原始整数 4",
  "Raw Ints": "原始整数",
  "Reaper": "钐镰客",
  "Reaper Shroud": "钐镰客魂衣",
  "Recent": "最近",
  "Recent file limit": "近期文件限制数",
  "Red Mage": "赤魔法师",
  "Redo": "重做",
  "Redo ": "重做",
  "Refresh": "刷新",
  "Refresh write location each update": "每次刷新时更新写入地址",
  "Refs": "引用",
  "Remove": "移除",
  "Remove Replaced Texture": "移除被替换的材质",
  "Rename": "重命名",
  "Replace": "替换",
  "Replace sound file": "替换音效文件",
  "Replace TMB": "替换时间线",
  "Report an Issue": "提交 Issue",
  "Report this error": "上报错误",
  "Reset": "重置",
  "Reset to current directory": "重置为当前目录",
  "Reset#": "重置#",
  "Resources": "资源",
  "Result": "结果",
  "Reverb FAC": "混音强度系数",
  "Reverb Type": "混响类型",
  "Revised B": "修改后蓝色",
  "Revised Color": "修改后颜色",
  "Revised G": "修改后绿色",
  "Revised Pos X": "修改后 X 轴坐标",
  "Revised Pos Y": "修改后 Y 轴坐标",
  "Revised Pos Z": "修改后 Z 轴坐标",
  "Revised Position": "修改后位置",
  "Revised R": "修改后红色",
  "Revised Rot X": "修改后 X 轴旋转",
  "Revised Rot Y": "修改后 Y 轴旋转",
  "Revised Rot Z": "修改后 Z 轴旋转",
  "Revised Rotation": "修改后旋转",
  "Revised Scale": "修改后缩放",
  "Revised Scale (Combined)": "修改后缩放(整体)",
  "Revised Scale X": "修改后 X 轴缩放",
  "Revised Scale Y": "修改后 Y 轴缩放",
  "Revised Scale Z": "修改后 Z 轴缩放",
  "Right": "右",
  "Right calves": "右小腿",
  "Right foot": "右脚",
  "Right forearm": "右前臂",
  "Right hand": "右手",
  "Right hand weapon": "右手武器",
  "Right shoulder": "右肩",
  "Ring Fan": "环形扇叶排布",
  "Roegadyn F": "鲁加族女性",
  "Roegadyn M": "鲁加族男性",
  "Rotation": "旋转",
  "Rotation Add": "旋转增量",
  "Rotation Add X": "X 轴旋转增量",
  "Rotation Add Y": "Y 轴旋转增量",
  "Rotation Add Z": "Z 轴旋转增量",
  "Rotation Base": "旋转基数",
  "Rotation Base X": "X 轴旋转基值",
  "Rotation Base Y": "Y 轴旋转基值",
  "Rotation Base Z": "Z 轴旋转基值",
  "Rotation Direction Base": "旋转方向基准",
  "Rotation Order": "旋转顺序",
  "Rotation Speed": "旋转速度",
  "Rotation Start X": "旋转起始 X 轴分量",
  "Rotation Start Y": "旋转起始 Y 轴分量",
  "Rotation Start Z": "旋转起始 Z 轴分量",
  "Rotation Velocity": "旋转速度",
  "Rotation Velocity X": "X 轴旋转速度",
  "Rotation Velocity Y": "Y 轴旋转速度",
  "Rotation Velocity Z": "Z 轴旋转速度",
  "Routing": "路由",
  "Row {idx}": "行 {idx}",
  "Sage": "贤者",
  "Samples to Bytes": "样本转字节",
  "Samurai": "武士",
  "Save": "保存",
  "Save as": "另存为",
  "Save As": "另存为",
  "Save VFX nodes here using the button:": "使用按钮在这里保存视效节点",
  "Saved GLTF to: ": "已保存 GLTF 至: ",
  "Saved item to VFX library": "已保存至视效库",
  "Saved workspace": "工作区已保存",
  "Scale": "缩放",
  "Scale A": "透明度",
  "Scale B": "蓝",
  "Scale by Parent": "根据父级缩放",
  "Scale Curve": "缩放曲线",
  "Scale End": "结束缩放",
  "Scale End X": "缩放结束 X 轴分量",
  "Scale End Y": "缩放结束 Y 轴分量",
  "Scale G": "绿",
  "Scale R": "红",
  "Scale Random Link": "随机缩放关联",
  "Scale Random X 0": "X 轴随机缩放 - 0",
  "Scale Random X 1": "X 轴随机缩放 - 1",
  "Scale Random Y 0": "Y 轴随机缩放 - 0",
  "Scale Random Y 1": "Y 轴随机缩放 - 1",
  "Scale Start": "起始缩放",
  "Scale Start X": "缩放起始 X 轴分量",
  "Scale Start Y": "缩放起始 Y 轴分量",
  "Scale X Random": "随机 X 轴缩放",
  "Scale Y Random": "随机 Y 轴缩放",
  "Scaling Scale": "缩放比例",
  "Scheduler": "调度器",
  "Scholar": "学者",
  "Search": "搜索",
  "Search :": "搜索 :",
  "Search Attribute Id": "搜索属性 ID",
  "Seat {i + 1}": "座位 {i + 1}",
  "Second Condition": "第二条件",
  "Seconds to Bytes": "秒转字节",
  "SELECT": "选择",
  "Select {UiUtils.GetArticle( name )} {name}": "请选择 {name}...",
  "Select a File": "选择文件",
  "Select a Save Location": "选择保存位置",
  "Select a timeline track...": "选择一条时间线...",
  "Select a Workspace File": "选择一个工作区文件",
  "Select an item...": "请选择...",
  "Select both a loaded VFX and a VFX to replace in order to use the spawn function": "为使用生成功能，请选择一个已加载的视效和一个用于替换的视效",
  "Select Command": "选择命令",
  "Select Index": "选择索引",
  "Selected color": "已选颜色",
  "Selected size": "已选大小",
  "Self Argument": "自引用参数",
  "SeqContentBar": "序列编辑器内容栏",
  "SeqScollBar": "序列编辑器滚动条",
  "SeqTopBar": "序列编辑器顶栏",
  "Settings": "设置",
  "Shade Black": "黑色阴影",
  "Shape": "形状",
  "Show Edges": "显示边缘",
  "Show Emitter Vertices": "显示发射器顶点",
  "Show source column": "显示来源表格",
  "Simple Animation": "简易动画",
  "Simulate Loop Start/End": "模拟循环开始/结束",
  "Size": "大小",
  "Skeleton Type": "骨架类型",
  "Soft Particle Fade Range": "柔性粒子淡化范围",
  "Softness": "模糊度",
  "Softness Random": "随机模糊度",
  "Sort": "排序",
  "Sort Key Offset": "排序键偏移值",
  "Sound Id": "音频 ID",
  "Sound Id 1": "音频 ID 1",
  "Sound Id 2": "音频 ID 2",
  "Sound Index": "音频索引",
  "Sound Index (-1 if no sound)": "音效索引 (无音效则为 -1)",
  "Sound Label High": "高音标签",
  "Sound Label Low": "低音标签",
  "Sound Position": "音频位置",
  "Sounds": "音效",
  "Spawn": "生成",
  "Spawn on ground (Vfx only)": "在地面生成(仅限视效)",
  "Spawn on self (Vfx only)": "在自身生成(仅限视效)",
  "Spawn on target (Vfx only)": "在目标生成(仅限视效)",
  "Start": "开始",
  "Start Frame": "起始帧",
  "Start Frame Null Update": "起始帧空更新",
  "Start Hidden": "初始隐藏",
  "Start Position": "开始位置",
  "Start Time": "开始时间",
  "Start Visibility": "可见性开始",
  "Status": "状态",
  "Strength": "强度",
  "Sub-Sound Type": "子声音类型",
  "Summon Animation": "召唤动画",
  "Summon Weapon": "召唤武器",
  "Summon Weapon Visibility": "召唤武器可见性",
  "Summoner": "召唤师",
  "Tabs": "栏",
  "Tag Number": "标签编号",
  "Target": "目标",
  "Target Argument": "目标参数",
  "Target Binder": "目标绑定器",
  "Target Command": "目标命令",
  "Target Emitter": "目标发射器",
  "Target Index": "目标索引",
  "Target Particle": "目标粒子",
  "Target Type": "目标类型",
  "Temp file location": "缓存文件位置",
  "Templates": "模板",
  "Terrain VFX": "地形视效",
  "Texture": "材质",
  "Textures": "材质",
  "The 3D preview does not currently work with facial animations (smile:frown:etc.)": "3D 预览功能目前无法预览面部动画(如: 微笑、皱眉等)",
  "The file Already Exists !##{Title}{Id}OverWriteDialog": "该文件已存在 !##{Title}{Id}OverWriteDialog",
  "This animation has Havok index: {HavokIndex}": "此动画的 Havok 索引为: {HavokIndex}",
  "This item does not have a VFX. See the link below for information on adding one": "这一对象没有预置视觉效果，你可以点击下面的链接查阅如何为其添加一个视效(英文)",
  "This parameter is set in the game's Excel sheet, and cannot be removed with VFXEditor": "这一参数位于游戏的数据表格中，无法被 VFXEditor 移除",
  "Time": "时间",
  "Timeline": "时间线",
  "Timeline Editor": "时间线编辑器",
  "Timeline Index": "时间线索引",
  "Timelines": "时间线",
  "TMB": "时间线",
  "TMB data imported": "已导入时间线数据",
  "TmbReader constructor failed for {magic}": "TmbReader 构造函数在 {magic} 处发生错误",
  "Tools": "工具",
  "Track {idx}": "轨道 {idx}",
  "Track #{idx}": "轨道 #{idx}",
  "Track Index": "轨道序列",
  "Transform Skip": "跳过变换",
  "Tried to put folder into itself": "尝试将文件夹放入自身",
  "Trigger": "触发器",
  "Trigger Count": "触发器数",
  "Triggers": "触发器",
  "Unassign {name}": "取消设置 {name}",
  "Unassign field": "取消设置字段",
  "Unassign/{name}": "取消设置/{name}",
  "Undo": "撤销",
  "Undo history size": "可回退的历史操作步数",
  "Unknown 1": "未知 1",
  "Unknown 2": "未知 2",
  "Unknown 3": "未知 3",
  "Unknown 4": "未知 4",
  "Unknown 5": "未知 5",
  "Unknown 6": "未知 6",
  "Unknown 7": "未知 7",
  "Unknown 8": "未知 8",
  "Unknown 9": "未知 9",
  "Unknown 10": "未知 10",
  "Unknown 11": "未知 11",
  "Unknown 12": "未知 12",
  "Unknown Entry {magic}": "未知条目 {magic}",
  "Unlock Loop Point": "解锁循环点",
  "Up Time": "运行时间",
  "Update": "刷新",
  "UPDATE": "刷新",
  "Update field value": "更新字段值",
  "Upper Limit": "上限",
  "Use custom window color": "使用自定义窗口颜色",
  "Use Edge": "使用边缘",
  "Use Face Library": "使用面部库",
  "User Id": "用户 ID",
  "Utilities": "工具",
  "Utilities to generate byte values which can be used for loop start/end": "用于生成可用于循环起始/结束的字节值的工具",
  "UV Cell U": "平面坐标系水平分量",
  "UV Cell V": "平面坐标系垂直分量",
  "UV Interval": "平面坐标区间",
  "UV Loop Count": "平面坐标循环数",
  "UV Random": "随机平面坐标",
  "UV Reverse": "平面坐标反转",
  "UV View": "UV 视图",
  "Value": "值",
  "Variant": "分支",
  "Variant Id": "分支 ID",
  "Variant: ": "分支: ",
  "Velocity Flattery Rate": "速度平缓率",
  "Velocity Flattery Speed": "速度平缓速",
  "Velocity Max": "速度最大值",
  "Velocity Min": "速度最小值",
  "Velocity Random Z": "随机 Z 轴速度",
  "Velocity Random X": "随机 X 轴速度",
  "Velocity Random Y": "随机 Y 轴速度",
  "Verified": "验证通过",
  "Version": "版本",
  "Vertex Count": "顶点数量",
  "Vertices: {Vertexes.Vertexes.Count} Indexes: {Indexes.Indexes.Count}": "顶点: {Vertexes.Vertexes.Count} 索引: {Indexes.Indexes.Count}",
  "VFX": "视效",
  "VFX editor and viewer": "游戏视效编辑器、查看器",
  "VFX path overlay": "视效路径窗口",
  "VFX Version: {UiVersion[0]}.{UiVersion[1]}.{UiVersion[2]}.{UiVersion[3]}": "VFX 版本: {UiVersion[0]}.{UiVersion[1]}.{UiVersion[2]}.{UiVersion[3]}",
  "vfx_workspace.json does not exist": "vfx_workspace.json 不存在",
  "VFX:animation:and sound editing plugin. Icon by PAPACHIN": "视效、动画、音效编辑插件 | 图标由 PAPACHIN 绘制\n本地化翻译由 AtmoOmen 维护",
  "Videos": "图片",
  "Viera F": "维埃拉族女性",
  "Viera M": "维埃拉族男性",
  "Voice": "声音",
  "Voiceline Number": "语音台词编号",
  "Volume": "音量",
  "WARNING: Add a selectable item first!": "警告: 请先添加一个可选择的物体!",
  "WARNING: Add an item!": "警告: 请先添加一个物体!",
  "WARNING: CYCLICAL": "警告: 循环",
  "Warning: files do not match at {idx:X8} : {data[idx]:X8} / {original[idx]:X8}": "警告: 此处文件与游戏原始文件不匹配 - {idx:X8} : {data[idx]:X8} / {original[idx]:X8}",
  "Warrior": "战士",
  "Weapon": "武器",
  "Weapon Id": "武器 ID",
  "Weapon Position": "武器位置",
  "Weapon Size": "武器大小",
  "Which channels to play when previewing the audio file. Does not affect the .scd file": "在预览音频文件时播放哪些声道。不影响 .scd 文件",
  "White Mage": "白魔法师",
  "Width": "宽度",
  "Width Begin": "起始宽度",
  "Width Center": "中心宽度",
  "Width End": "结束宽度",
  "Width Random": "随机宽度",
  "Wiki + Guides": "Wiki + 指南(英文)",
  "Windmill UV Type": "风车 UV 映射类型",
  "Wireframe": "线框",
  "Workspace": "工作区",
  "Would you like to Overwrite it ?": "你想要覆盖该文件吗?",
  "Write location: ": "写入路径: ",
  "Wrote {1} file to {0}": "已将 {1} 个文件写入 {0}",
  "Zone": "区域",
  "Scd Editor": "音频编辑器",
  "Scd Select [LOADED]": "选择文件 [加载]",
  "Scd Select [REPLACED]": "选择文件 [替换]",
  "File Select [LOADED]": "选择文件 [加载]",
  "File Select [REPLACED]": "选择文件 [替换]",
  "Eid Select [LOADED]": "选择文件 [替换]",
  "Eid Select [REPLACED]": "选择文件 [替换]",
  "Pap Select [LOADED]": "选择文件 [加载]",
  "Pap Select [REPLACED]": "选择文件 [替换]",
  "Tmb Editor": "时间线编辑器",
  "Tmb Select [LOADED]": "选择文件 [加载]",
  "Tmb Select [REPLACED]": "选择文件 [替换]",
  "Github": "GitHub",
  "Uld Editor": "界面编辑器",
  "Uld Select [LOADED]": "选择文件 [加载]",
  "Uld Select [REPLACED]": "选择文件 [替换]",
  "Target Effector": "目标效果器",
  "Injection Angle Z": "Z 轴注入角度",
  "Injection Angle Z Random": "随机 Z 轴注入角度",
  "Rotation Compute Order": "旋转计算顺序",
  "Coord Compute Order": "坐标计算顺序",
  "Draw Mode": "绘制模式",
  "Culling Type": "剔除类型",
  "Directional Light": "定向光",
  "Enviornmental Light": "环境光",
  "UV Precision": "平面坐标精度",
  "Draw Priority": "绘制优先级",
  "Depth Test": "深度测试",
  "Depth Write": "深度写入",
  "Soft Particle": "柔性粒子",
  "Collision Type": "碰撞类型",
  "Apply Tone Map": "应用色调映射",
  "Apply Fog": "应用雾效",
  "Enable Clip Near": "启用近裁剪",
  "Enable Clip Far": "启用远裁剪",
  "Clip Near Start": "近裁剪开始位置",
  "Clip Near End": "近裁剪结束位置",
  "Clip Far Start": "远裁剪开始位置",
  "Clip Far End": "远裁剪结束位置",
  "Clip Base Point": "裁剪基准点",
  "UV Set Count": "平面坐标集数量",
  "Apply Rate Environment": "应用环境光强度",
  "Apply Rate Directional": "应用定向光强度",
  "Apply Rate Light Buffer": "应用光缓冲率",
  "Depth Offset": "深度偏移",
  "Use Simple Animation": "使用简易动画",
  "Rotation Velocity X Random": "随机 X 轴旋转速度",
  "Rotation Velocity Y Random": "随机 Y 轴旋转速度",
  "Rotation Velocity Z Random": "随机 Z 轴旋转速度",
  "Texture Color 1": "材质颜色 1",
  "Texture Color 2": "材质颜色 2",
  "Texture Color 3": "材质颜色 3",
  "Texture Color 4": "材质颜色 4",
  "Clip Near": "近裁剪",
  "Clip Far": "远裁剪",
  "UV Sets": "平面坐标集",
  "Particle {GetIdx()}({ParticleVariety.GetValue()})": "粒子 {GetIdx()}({ParticleVariety.GetValue()})",
  "Binder {GetIdx()}({BinderVariety.GetValue()})": "绑定器 {GetIdx()}({BinderVariety.GetValue()})",
  "Start To Global Direction": "起始点至全局方向",
  "VFX Scale": "视效缩放",
  "VFX Scale Bias": "视效缩放偏移",
  "VFX Scale Depth Offset": "视效缩放深度偏移",
  "VFX Scale Interpolation": "视效缩放插值",
  "Transform Scale": "变换缩放",
  "Transform Scale Depth Offset": "变换缩放深度偏移",
  "Transform Scale Interpolation": "变换缩放插值",
  "Following Target Orientation": "跟随目标面向",
  "Document Scale Enabled": "启用文档缩放",
  "Adjust to Screen": "适应屏幕",
  "BET (Unknown)": "BET (未知)",
  "Binder Rotation Type": "绑定器选择类型",
  "Properties Start": "起始属性",
  "Properties 1": "属性 1",
  "Properties 2": "属性 2",
  "Properties Goal": "目标属性",
  "Particle": "粒子",
  "Texture Normal": "法线材质",
  "+ Texture Normal": "+ 法线材质",
  "Texture Filter": "材质筛选器",
  "Texture Border U": "水平材质边界",
  "Texture Border V": "垂直材质边界",
  "Texture Index": "材质索引",
  "Distance": "距离",
  "Distance Random": "随机距离",
  "Carry Over Factor": "传递因子",
  "Carry Over Factor Random": "随机传递因子",
  "Spring Strength": "弹簧强度",
  "Bind Point Type": "绑定点类型",
  "Bind Target Point Type": "绑定目标点类型",
  "Bind Point Id": "绑定点 ID",
  "Coord Update Frame": "坐标更新帧",
  "Ring Enabled": "启用环",
  "Ring Progress Time": "环进度时间",
  "Ring Position X": "X 轴环位置",
  "Ring Position Y": "Y 轴环位置",
  "Ring Position Z": "Z 轴环位置",
  "Ring Radius": "环半径",
  "Ring Position": "环位置",
  "Binder": "绑定器",
  "Ctrl+Left Click": "Ctrl + 左键",
  "to add a new point": "以添加一个新的点",
  "Left Click": "单击左键",
  "to selected a point": "以选择一个点",
  "Shift": "按住 Shift 键",
  "to select multiple points": "以多选点",
  "Toggle replacement": "切换替换模式",
  "Loaded {Id}": "已载入的 {Id}",
  "{Id} Being Replaced": "被替换的 {Id}",
  "Version {UiVersion[0]}.{UiVersion[1]}.{UiVersion[2]}.{UiVersion[3]}": "版本 {UiVersion[0]}.{UiVersion[1]}.{UiVersion[2]}.{UiVersion[3]}",
  "No textures saved...": "无已保存的材质",
  "No textures have been replaced...": "无已替换的材质",
  "TMB:": "时间线:",
  "{Selected.Name} Start": "{Selected.Name} 开始",
  "Click to view more information on the VFXEditor wiki": "点击以在 VFXEditor Wiki 上了解更多信息(英文)",
  "Actors": "对象",
  "F-Curves": "F 曲线",
  "These are leftover tracks which are never actually triggered, and are only useful for research purposes": "以下为游戏内部遗留的音轨，它们从未被实际触发过，此处仅做研究用",
  "Unused": "未使用",
  "Use Lua Condition": "使用 Lua 条件",
  "Lock Translation": "锁定平移",
  "Create new bone at root": "在根部创建新骨骼",
  "Expand all tree nodes": "展开所有树状节点",
  "Parent": "父级",
  "Create sub-bone": "创建子骨骼",
  "Invalid SKLB version: {Version1:X4} {Version2:X4}": "无效的骨骼版本: {Version1:X4} {Version2:X4}",
  "Bones": "骨骼",
  "Mappings": "映射",
  "Sklb Editor": "骨骼编辑器",
  "Sklb Select [LOADED]": "选择文件 [加载]",
  "Sklb Select [REPLACED]": "选择文件 [替换]",
  "Parent 1": "父级 1",
  "Parent 2": "父级 2",
  "Parent 3": "父级 3",
  "Parent 4": "父级 4",
  "LoD Bones 1": "LoD 骨骼 1",
  "LoD Bones 2": "LoD 骨骼 2",
  "LoD Bones 3": "LoD 骨骼 3",
  "Connect Bones 1": "连接骨骼 1",
  "Connect Bones 2": "连接骨骼 2",
  "Connect Bones 3": "连接骨骼 3",
  "Connect Bones 4": "连接骨骼 4",
  "Header Version: [OLD]": "头版本 [旧]",
  "Simple Mappings": "简单映射",
  "Mapping {idx}": "映射 {idx}",
  "Mapped Skeleton Bone": "骨骼节点映射",
  "This Skeleton Bone": "该骨骼节点",
  "Translation": "平移",
  "Part Lists": "分部列表",
  "Components": "组件",
  "Widgets": "控件",
  "Parentheses color": "括号颜色",
  "Function color": "函数颜色",
  "Literal color": "字面值颜色",
  "Variable color": "变量颜色",
  "Exports the selected items, as well as any dependencies they have (such as particles depending on textures). It is recommended to leave this selected.": "导出选中项与它们的依赖关系 (如: 依赖材质的例子效果)。推荐选中此项",
  "Bone Connect Index": "骨骼连接索引",
  "Header Version: [NEW]": "头版本 [新]",
  "Parents": "父级",
  "Activated": "已激活",
  "Version: {Version}": "版本: {Version}",
  "Slope": "坡度",
  "Look At": "望向",
  "FootIK found, please report this": "发现 FootIK, 请上报此情况",
  "Skp Select [LOADED]": "选择文件 [加载]",
  "Skp Select [REPLACED]": "选择文件 [替换]",
  "Parameter": "参数",
  "Group": "组",
  "Setup Parameters": "设置参数",
  "Groups": "组",
  "Setup Parameters Index": "设置参数索引",
  "Parent Bone Name": "父级骨骼名称",
  "Limit Angles": "角度限制",
  "Forward Rotation": "前向旋转",
  "Limit Angle": "角度限制",
  "Eye Positions": "眼部位置",
  "Gain": "增益",
  "Parameters {Index.Value}": "参数 {Index.Value}",
  "Data Type": "数据类型",
  "Collision": "碰撞",
  "Simulation": "模拟",
  "Phyb Editor": "碰撞体编辑器",
  "Phyb Select [LOADED]": "选择文件 [加载]",
  "Phyb Select [REPLACED]": "选择文件 [替换]",
  "Start Bone": "起始骨骼",
  "End Bone": "结束骨骼",
  "Start Offset": "起始偏移",
  "End Offset": "结束偏移",
  "Bone": "骨骼",
  "Bone Offset 1": "骨骼偏移 1",
  "Bone Offset 2": "骨骼偏移 2",
  "Bone Offset 3": "骨骼偏移 3",
  "Bone Offset 4": "骨骼偏移 4",
  "Bone Offset": "骨骼偏移",
  "Thickness": "厚度",
  "[ELLIPSOID/NORMAL PLANE/THREE-POINT PLANE]": "[椭球/法平面/三点平面]",
  "Chain Id": "链 ID",
  "Node Id": "节点 ID",
  "Stiffness": "刚度",
  "Collision Radius": "碰撞半径",
  "Attract by Animation": "以动画吸引",
  "Wind Scale": "风力缩放",
  "Gravity Scale": "重力缩放",
  "Cone Max Angle": "锥体最大角度",
  "Cone Axis Offset": "锥体轴偏移",
  "Constraint Plane Normal": "约束平面法线",
  "Collision Flags": "碰撞标志",
  "Continuous Collision Flags": "持续碰撞标志",
  "Collision Name": "碰撞名称",
  "Chain Id 1": "链 ID 1",
  "Chain Id 2": "链 ID 2",
  "Node Id 1": "节点 ID 1",
  "Node Id 2": "节点 ID 2",
  "Friction": "摩擦",
  "Dampening": "阻力",
  "Repulsion": "斥力",
  "Stretch Stiffness": "延申刚度",
  "Compress Stiffness": "压缩刚度",
  "Version: {Version} DirectX: {DxVersion}": "版本: {Version} DirectX: {DxVersion}",
  "Vertex Shaders": "顶点着色器",
  "Pixel Shaders": "像素着色器",
  "Material Parameters": "材质参数",
  "Constants": "常量",
  "Samplers": "采样",
  "Nodes": "节点",
  "Aliases": "别称",
  "System": "系统",
  "Scene": "场景",
  "Material": "材质",
  "Sub-View": "子视图",
  "Shpk Editor": "着色器编辑器",
  "Shpk Select [LOADED]": "选择文件 [加载]",
  "Shpk Select [REPLACED]": "选择文件 [替换]",
  "Key {idx} (0x{Id.Value:X4})": "键 {idx} (0x{Id.Value:X4})",
  "Offset": "偏移",
  "Selector": "选择器",
  "Node Index": "节点索引",
  "Passes": "通道",
  "Pass Indexes:": "通道索引:",
  "Vertex Shader Index": "顶点着色器索引",
  "Pixel SHader Index": "像素着色器索引",
  "Pixel Shader Index": "像素着色器索引",
  "Slot": "栏",
  "Size (bytes)": "大小 (字节)",
  "Ids do not match": "ID 不符",
  "Unknown data": "未知数据",
  "Code": "编码",
  "Manually enter a string value to be converted to Crc32": "手动输入一个字符串值以转换为 Crc32",
  "String to be converted": "待转换的字符串值",
  "toggle ui": "打开主界面",
  "Emitter {GetIdx()} ({EmitterVariety.GetValue()})": "发射器 {GetIdx()} ({EmitterVariety.GetValue()})",
  "Binder {GetIdx()} ({BinderVariety.GetValue()})": "绑定器 {GetIdx()} ({BinderVariety.GetValue()})",
  "In-game .{Extension} file, eg: vfx/common/eff/wp_astro1h.{Extension}": "游戏内 .{Extension} 文件, 例如: vfx/common/eff/wp_astro1h.{Extension}",
  "Delay": "延迟",
  "Timeline [{invalidTimeline.GetText()}] is Missing a Value": "时间线 [{invalidTimeline.GetText()}] 缺少数值",
  "Calculate UV": "UV 计算方式",
  "Scroll": "滚动",
  "Rotation Random": "随机旋转",
  "Raw Integers": "原始整数",
  "Clip {GetIdx()} ({Type.Value})": "片段 {GetIdx()} ({Type.Value})",
  "Minimum Trigger": "最小触发",
  "Maximum Trigger": "最大触发",
  "Effector {GetIdx()} ({EffectorVariety.GetValue()})": "效果器 {GetIdx()} ({EffectorVariety.GetValue()})",
  "Particle {GetIdx()} ({ParticleVariety.GetValue()})": "粒子 {GetIdx()} ({ParticleVariety.GetValue()})",
  "Layers": "层",
  "+ Texture Reflection": "+ 材质反射",
  "Texture Reflection": "材质反射",
  "Use Screen Copy": "使用屏幕复制",
  "Calculate Color": "颜色计算方式",
  "Rate": "速率",
  "Distort UV 1": "UV 扭曲 1",
  "Distort UV 2": "UV 扭曲 2",
  "Distort UV 3": "UV 扭曲 3",
  "Distort UV 4": "UV 扭曲 4",
  "UV Set Index": "平面坐标集索引",
  "+ Texture Distortion": "+ 材质扭曲",
  "Texture Distortion": "材质扭曲",
  "Texture Border": "材质边框",
  "+ Texture Palette": "+ 材质调色",
  "Texture Palette": "材质调色",
  "Format: {Format}  Mips: {MipLevels}  Size: {Width}x{Height}": "格式: {Format}  Mips: {MipLevels}  大小: {Width}x{Height}",
  "Ability Delay": "技能延迟",
  "Loaded .pap resources can be found in File > Tools > Loaded Files": "已加载的 .pap 资源可以在 文件 > 工具 > 已加载文件 中找到",
  "Loaded Files": "已加载文件",
  "Lua Variables": "Lua 变量",
  "Pools: 0x{manager:X8}": "池: 0x{manager:X8}",
  "Dynamic: 0x{Plugin.ResourceLoader.LuaActorVariables:X8}": "动态: 0x{Plugin.ResourceLoader.LuaActorVariables:X8}",
  "Pool {pool.Id}": "池 {pool.Id}",
  "Current Value": "当前值",
  "Name": "名称",
  "Index": "索引",
  "Operation": "操作",
  "Float Value": "浮点值",
  "Pool": "池",
  "VAR[{pool},{index}]": "变量[{pool},{index}]",
  "Up": "上",
  "Down": "下",
  "Cursor": "指针",
  "Unknown": "未知",
  "Offset X": "X 轴偏移",
  "Offset Y": "Y 轴偏移",
  "{localPath} is the wrong file type": "{localPath} 文件类型错误",
  "{Id} file loaded": "{Id} 文件已加载",
  "Game file: [{gamePath}] does not exist": "游戏文件: [{gamePath}] 不存在",
  "{gamePath} is the wrong file type": "{gamePath} 文件类型错误",
  "VFXEditor does not have access to {Plugin.Configuration.WriteLocation}. Please go to [File > Settings] and change it, then restart your game": "VFXEditor 没有 {Plugin.Configuration.WriteLocation} 的访问权限. 请到 [文件 > 设置] 更改路径并重启游戏",
  "Log Vfx triggers": "记录 VFX 触发",
  "Show tab bar": "显示标签页栏",
  "Visibility": "可见性",
  "Export Havok": "导出 Havok",
  "No Havok data": "无 Havok 数据",
  "Export All Motions": "导出所有动作",
  "Face Animation": "面部动画",
  "Animation (PAP Only)": "动画 (仅 PAP)",
  "Original Skeleton Name": "原始骨骼名称",
  "Blend Hint": "混合提示",
  "Motion": "动作",
  "Tracks": "轨道",
  "Loop: [{motionData.Loop}] Lip: [{motionData.Lip}] Blink: [{motionData.Blink}]": "循环: [{motionData.Loop}] 嘴部: [{motionData.Lip}] 眼部: [{motionData.Blink}]",
  "These values are hard-coded in the game's MotionTimeline sheet, and are based on the animation name": "这些值基于特定的动画名称硬编码于游戏的 MotionTimeline 表格中",
  "Fade In Time": "淡入时间",
  "Fade Out Time": "淡出时间",
  "Texture Id": "材质 Id",
  "Show HD": "显示 HD 素材",
  "Icon Id": "图标 ID",
  "Drag Arrow": "拖拽箭头",
  "Drop Arrow": "放置箭头",
  "Ignore Input": "忽略输入",
  "Nodes referencing this component: {NumNodesReferencing}": "引用该组件的节点数: {NumNodesReferencing}",
  "Component {GetIdx()} ({Type.Value})": "组件 {GetIdx()} ({Type.Value})",
  "Text Node Id": "文本节点 ID",
  "Background Node Id": "背景节点 ID",
  "Is Component Node": "是否为组件节点",
  "Parent Id": "父级 ID",
  "Next Sibling Id": "下一兄弟节点 ID",
  "Prev Sibling Id": "前一兄弟节点 ID",
  "Component Id": "组件 ID",
  "Tab Index": "标签页索引",
  "Origin X": "原点 X",
  "Origin Y": "原点 Y",
  "Multiply Red": "红色相乘",
  "Multiply Green": "绿色相乘",
  "Multiply Blue": "蓝色相乘",
  "Add Red": "增加红色",
  "Add Green": "增加绿色",
  "Add Blue": "增加蓝色",
  "Timeline Id": "时间线 ID",
  "Unknown node type {DelayedNodeType} / {DelayedSize} @ {reader.BaseStream.Position:X8}": "未知节点类型 {DelayedNodeType} / {DelayedSize} @ {reader.BaseStream.Position:X8}",
  "Node {GetIdx()} ({suffix})": "节点 {GetIdx()} ({suffix})",
  "Child Node Id": "子级节点 ID",
  "Part List Id": "分部列表 ID",
  "Part Id": "分部 Id",
  "Number Width": "数字宽度",
  "Comma Width": "逗号宽度",
  "Space Width": "空格宽度",
  "Alignment": "对齐",
  "Flip H": "水平翻转",
  "Flip V": "垂直翻转",
  "Wrap": "环绕",
  "Grid Parts Type": "网格部分类型",
  "Grid Render Type": "网格渲染类型",
  "Top Offset": "顶部偏移",
  "Bottom Offset": "底部偏移",
  "Left Offset": "左部偏移",
  "Right Offset": "右部偏移",
  "Switch between degrees and radians": "在度和弧度之间转换",
  "Unsupported": "不支持",
  "Verification is not supported for this file or file type": "不支持验证此种文件的有效性",
  "Armor": "装备",
  "Show Bone Names": "显示骨骼名称",
  "Could not read file: {SklbPreviewPath}": "无法读取文件: {SklbPreviewPath}",
  "Capsules": "胶囊",
  "Ellipsoids": "椭球",
  "Normal Planes": "法平面",
  "Three-Point Planes": "三点平面",
  "Spheres": "球",
  "Max Speed": "最大速度",
  "Collision Dampening": "碰撞阻尼",
  "Repulsion Strength": "斥力强度",
  "Last Bone Offset": "最后骨骼偏移",
  "Node {idx + 1}": "节点 {idx + 1}",
  "Collision Objects": "碰撞物体",
  "Wind": "风",
  "Constraint Loop": "约束循环",
  "Collision Loop": "碰撞循环",
  "Collision Connectors": "碰撞连接器",
  "Chains": "链接",
  "Connectors": "连接器",
  "Attracts": "吸引",
  "Pins": "固定",
  "Springs": "弹簧",
  "Post Alignments": "后置对齐",
  "Hair {hairId}": "发型 {hairId}",
  "Hair": "发型",
  "Face": "脸型",
  "Body": "身体",
  "Data Version: [NEW]": "数据版本: [新]",
  "Data Version: [OLD]": "数据版本: [旧]",
  "Accessory": "配件",
  "Atch Editor": "武器状态编辑器",
  "Atch Select [LOADED]": "武器状态选择 [选择]",
  "Atch Select [REPLACED]": "武器状态选择 [替换]",
  "Attach": "附加",
  "Undo##Menu": "撤销##Menu",
  "Redo##Menu": "重做##Menu",
  "Model {GetIdx()}": "模型 {GetIdx()}",
  "Scheduler {GetIdx()}": "调度器 {GetIdx()}",
  "Texture {GetIdx()}": "材质 {GetIdx()}",
  "Timeline {GetIdx()}": "时间线 {GetIdx()}",
  "Color To Alpha": "颜色值转透明度",
  "Calculate Alpha": "透明度计算方式",
  "Previous Frame Copy": "复制前一帧",
  "Delete {Name}": "删除 {Name}",
  "Mask Texture": "遮罩材质",
  "Delete Texture Color 1": "删除材质颜色 1",
  "+ Texture Color 1": "+ 材质颜色 1",
  "Mask Index": "遮罩索引",
  "TexN Random": "随机 TexN",
  "Sound": "音效",
  "Voiceline": "语音台词",
  "Greataxe": "大斧",
  "Bow": "弓",
  "Nouliths": "贤具",
  "Gunblade": "枪刃",
  "Globe": "天球仪",
  "Book": "魔导书",
  "Gun": "火枪",
  "Scythe": "镰刀",
  "Katana": "武士刀",
  "Rapier": "刺剑",
  "Spear": "长枪",
  "Greatsword": "双手剑",
  "Alchemist": "炼金术师",
  "Armorer": "铸甲匠",
  "Culinarian": "烹调师",
  "Goldsmith": "雕金匠",
  "Leatherworker": "制革匠",
  "Weaver": "裁衣匠",
  "Carpenter": "刻木匠",
  "Machinist Bag": "机工士弹匣",
  "Chakram": "战轮",
  "Glove": "手套",
  "Claw": "爪",
  "Drum": "鼓",
  "Fisher": "捕鱼人",
  "Flute": "笛",
  "Ninja Frog": "忍者烟雾",
  "Leatherworker/Culinarian": "制革匠/烹调师",
  "Fist Weapons": "格斗武器",
  "Machinist Deployable": "机工士召唤物",
  "Blacksmith/Armorer": "锻铁匠/铸甲匠",
  "Bard Harp": "吟游诗人乐器",
  "Botanist": "园艺工",
  "Samurai Sheath": "武士刀鞘",
  "Machinist Shotgun": "机工士霰弹枪",
  "Machinist Cannon": "机工士火枪",
  "Red Mage Focus": "赤魔法师刺剑水晶",
  "Miner": "采矿工",
  "Quiver": "箭囊",
  "Ninja Rabbit": "忍者兔子",
  "Blue Mage Rod": "青魔杖",
  "Shield": "盾",
  "Staff": "杖",
  "Sword": "剑",
  "Machinist Sniper": "机工士狙击枪",
  "Astrologian Deck": "占星术士卡牌",
  "Greatstaff": "巨杖",
  "Error previewing image {path}": "预览图像时发生错误 {path}",
  "Data of size 0x{Data?.Length:X8}": "数据大小 0x{Data?.Length:X8}",
  "Unknown Node Id 1": "未知节点 ID 1",
  "Unknown Node Id 2": "未知节点 ID 2",
  "Unknown Node Id 3": "未知节点 ID 3",
  "Unknown Node Id 4": "未知节点 ID 4",
  "Unknown Node Id 5": "未知节点 ID 5",
  "Unknown Node Id 6": "未知节点 ID 6",
  "Unknown Node Id 7": "未知节点 ID 7",
  "Unknown Node Id 8": "未知节点 ID 8",
  "Unknown Node Id 9": "未知节点 ID 9",
  "Unknown Node Id 10": "未知节点 ID 10",
  "Unknown Node Id": "未知节点 ID",
  "Item Margin": "项边距",
  "Basic Margin": "基本边距",
  "Unknown Margin": "未知边距",
  "Orientation": "取向",
  "Padding": "内边距",
  "Is Vertical": "是否垂直",
  "IME Color": "输入法颜色",
  "Text Id": "文本 ID",
  "Min": "最小值",
  "Max": "最大值",
  "Toggle": "切换",
  "Rows": "行",
  "Columns": "列",
  "Comma": "逗号",
  "Add": "新增",
  "Group Id": "组 ID",
  "Step": "步长",
  "Max Width": "最大宽度",
  "Max Lines": "最大行数",
  "Max Bytes": "最大字节数",
  "Max Chars": "最大字符数",
  "Charset": "字符集",
  "Charset Extra {i}": "额外字符集 {i}",
  "Flags 2": "标志 2",
  "Title Text Id": "标题文本 ID",
  "Subtitle Text Id": "副标题文本 ID",
  "Close Button": "关闭按钮",
  "Settings Button": "设置按钮",
  "Help Button": "帮助按钮",
  "Header": "顶栏",
  "Font Size": "字体大小",
  "Edge Color": "边缘颜色",
  "Sheet Type": "表格类型",
  "Character Spacing": "字符间距",
  "Line Spacing": "行间距",
  "Unknown component type {( int )Type.Value} / {pos + offset - reader.BaseStream.Position} @ {reader.BaseStream.Position:X8}": "未知组件类型 {( int )Type.Value} / {pos + offset - reader.BaseStream.Position} @ {reader.BaseStream.Position:X8}",
  "Texture {item.TextureId.Value}": "材质 {item.TextureId.Value}",
  "Part {idx} ({text})###{idx}": "分部 {idx} ({text})###{idx}",
  "Part List {GetIdx()}": "分部列表 {GetIdx()}",
  "End Frame": "结束帧",
  "Interpolation": "插值",
  "Deceleration": "减速",
  "Value 1": "值 1",
  "Value 2": "值 2",
  "Value 3": "值 3",
  "Label Id": "标签 ID",
  "Label Command": "标签命令",
  "Jump Id": "跳跃 ID",
  "Keyframe {idx}": "关键帧 {idx}",
  "Frames 1": "帧 1",
  "Frames 2": "帧 2",
  "Alignment Type": "对齐类型",
  "Widget {GetIdx()}": "控件 {GetIdx()}",
  "Export as a raw file": "导出为原始文件",
  "Dagger": "忍者匕首",
  "Binder {GetIdx()} ({Type.Value})": "绑定器 {GetIdx()} ({Type.Value})",
  "State {idx} ({state.Bone.Value})###{idx}": "状态 {idx} ({state.Bone.Value})###{idx}",
  "Minimum": "最小值",
  "Maximum": "最大值",
  "Parent Bone": "父级骨骼",
  "Light Shafts": "光束",
  "Glass": "玻璃",
  "Material Change": "材质变更",
  "Crest Change": "纹路变更",
  "Model Range": "模型范围",
  "Texture Range": "纹理范围",
  "Meshes": "网格",
  "Terrain Shadows": "地形阴影",
  "Water": "水",
  "Shadows": "阴影",
  "Vertical Fog": "垂直雾",
  "Terrain Shadow: stride={stride}": "地形阴影: 步幅={stride}",
  "Mesh": "网格",
  "Sub-Meshes": "子网格",
  "Bone Table Index": "骨骼表索引",
  "Preview": "预览",
  "3D Preview": "3D 预览",
  "Preview Images": "预览图像",
  "Preview Dye": "预览染色",
  "Index Buffer Streaming": "索引缓冲流",
  "Edge Geometry": "边缘几何",
  "Flags 1": "标志 1",
  "Model Clip Out Distance": "模型裁剪距离",
  "Shadow Clip Out Distance": "阴影裁剪距离",
  "Background Change Material Index": "背景更换材质索引",
  "Background Crest Change Material Index": "背景纹路更换材质索引",
  "Mesh:{meshCount}/{vertexDeclarationCount} Material:{materialCount}/{_materialCount} LoD:{lodCount}/{_lodCount}": "网格:{meshCount}/{vertexDeclarationCount} 材质:{materialCount}/{_materialCount} LoD:{lodCount}/{_lodCount}",
  "Extra LoD": "额外 LoD",
  "Bind Points": "绑定点",
  "Levels of Detail": "细节层次",
  "Bone Tables": "骨骼表",
  "Bounding Boxes": "包围盒",
  "Unknown Boxes": "未知盒",
  "Mdl Select [LOADED]": "选择文件 [加载]",
  "Mdl Select [REPLACED]": "选择文件 [替换]",
  "U Address Mode": "横轴地址模式",
  "V Address Mode": "纵轴地址模式",
  "LoD Bias": "LoD 偏移",
  "Minimum LoD": "最小 LoD",
  "Sampler {idx}": "采样器 {idx}",
  "Diffuse": "漫射",
  "Specular Strength": "镜面反射强度",
  "Specular": "镜面",
  "Gloss Strength": "光泽强度",
  "Emissive": "自发光",
  "Material Repeat X": "横轴材质重复",
  "Material Repeat Y": "纵轴材质重复",
  "Material Skew": "材质倾斜",
  "Dye": "染色",
  "[NO DYE VALUE]": "[无染色值]",
  "Gloss: %.1f": "光泽: %.1f",
  "Power: %.1f": "强度: %.1f",
  "Template": "模板",
  "Tile {Value}": "倾斜 {Value}",
  "Tile {i}": "倾斜 {i}",
  "Options": "选项",
  "Shader Options": "着色器选项",
  "Shader Flags": "着色器标志",
  "Color Sets": "颜色集",
  "Color Table": "颜色表",
  "Error reading shader {newPath}": "读取着色器 {newPath} 时发生错误",
  "Mtrl Select [LOADED]": "选择文件 [加载]",
  "Mtrl Select [REPLACED]": "选择文件 [替换]"
}